big_fiubrother_core_application/__init__.py
big_fiubrother_core_application/application.py
big_fiubrother_core_application/application_arguments.py
big_fiubrother_core_application/configuration.py
big_fiubrother_core_application/environment.py
big_fiubrother_core_application/logging_service.py
big_fiubrother_core_application/runtime_context.py
big_fiubrother_core_application/signal_handler.py
big_fiubrother_core_application-0.0.1.dist-info/METADATA
big_fiubrother_core_application-0.0.1.dist-info/WHEEL
big_fiubrother_core_application-0.0.1.dist-info/top_level.txt
big_fiubrother_core_application-0.0.1.dist-info/RECORD
