Metadata-Version: 2.1
Name: big-fiubrother-core-application
Version: 0.0.1
Summary: Frame for a micro service in the Big Fiubrother ecosystem
Home-page: https://github.com/BigFiuBrother/big-fiubrother-core
Author: Eduardo Neira
Author-email: aneira@fi.uba.ar
Project-URL: Bug Tracker, https://github.com/BigFiuBrother/big-fiubrother-core/issues
Classifier: Programming Language :: Python :: 3
Classifier: Operating System :: OS Independent
Requires-Python: >=3.6
